{"kaptCode":"A10023981","aptName":"탑석센트럴자이","sigunguName":"의정부시","umdName":"용현동","updatedAt":"2026-07-23","byArea":{"84㎡":{"avgPrice":70828,"tradeCount":40,"latestPrice":81000,"latestDate":"2026-07-16","recentHigh":{"within3M":true,"label":"최근 최고가","price":81000,"date":"2026-07-16","previousHighPrice":79000}},"105㎡":{"avgPrice":96333,"tradeCount":3,"latestPrice":98000,"latestDate":"2026-05-13","recentHigh":{"within3M":true,"label":"최근 최고가","price":98000,"date":"2026-05-13","previousHighPrice":96000}},"59㎡":{"avgPrice":52926,"tradeCount":89,"latestPrice":59000,"latestDate":"2026-07-13","recentHigh":{"within3M":true,"label":"최근 최고가","price":59800,"date":"2026-06-19","previousHighPrice":59000}},"75㎡":{"avgPrice":62685,"tradeCount":20,"latestPrice":66500,"latestDate":"2026-07-14","recentHigh":{"within3M":true,"label":"최근 최고가","price":67500,"date":"2026-05-15","previousHighPrice":65500}},"49㎡":{"avgPrice":43200,"tradeCount":4,"latestPrice":46000,"latestDate":"2026-07-11","recentHigh":{"within3M":true,"label":"최근 최고가","price":46000,"date":"2026-07-11","previousHighPrice":44300}}}}
