{"kaptCode":"A10027985","aptName":"강남자곡 힐스테이트","sigunguName":"강남구","umdName":"자곡동","updatedAt":"2026-06-25","byArea":{"84㎡":{"avgPrice":141544,"tradeCount":16,"latestPrice":175000,"latestDate":"2026-03-04","recentHigh":{"within3M":true,"label":"최근 최고가","price":175000,"date":"2026-03-04","previousHighPrice":174000}},"74㎡":{"avgPrice":132250,"tradeCount":10,"latestPrice":167000,"latestDate":"2026-02-02","recentHigh":{"within3M":true,"label":"최근 최고가","price":167000,"date":"2026-02-02","previousHighPrice":150000}},"59㎡":{"avgPrice":128941,"tradeCount":27,"latestPrice":154000,"latestDate":"2026-06-02","recentHigh":{"within3M":true,"label":"최근 최고가","price":157000,"date":"2026-02-28","previousHighPrice":151000}},"51㎡":{"avgPrice":119500,"tradeCount":7,"latestPrice":140000,"latestDate":"2026-06-12","recentHigh":{"within3M":true,"label":"최근 최고가","price":140000,"date":"2026-06-12","previousHighPrice":135000}}}}
