{"kaptCode":"A10023624","aptName":"검단신도시디에트르더힐","sigunguName":"서구","umdName":"원당동","updatedAt":"2026-06-21","byArea":{"84㎡":{"avgPrice":62131,"tradeCount":26,"latestPrice":62000,"latestDate":"2026-05-12","recentHigh":{"within3M":true,"label":"최근 최고가","price":67500,"date":"2026-02-06","previousHighPrice":66000}},"108㎡":{"avgPrice":71350,"tradeCount":7,"latestPrice":70000,"latestDate":"2026-05-10"},"75㎡":{"avgPrice":57406,"tradeCount":18,"latestPrice":72000,"latestDate":"2026-05-20","recentHigh":{"within3M":true,"label":"최근 최고가","price":72000,"date":"2026-05-20","previousHighPrice":65500}},"76㎡":{"avgPrice":57133,"tradeCount":24,"latestPrice":52000,"latestDate":"2026-06-15","recentHigh":{"within3M":true,"label":"최근 최고가","price":59500,"date":"2026-01-06","previousHighPrice":58300}},"109㎡":{"avgPrice":65760,"tradeCount":5,"latestPrice":66500,"latestDate":"2026-06-04"}}}
