{"kaptCode":"A10022605","aptName":"문수비스타동원","sigunguName":"남구","umdName":"무거동","updatedAt":"2026-07-19","byArea":{"74㎡":{"avgPrice":57125,"tradeCount":4,"latestPrice":58000,"latestDate":"2026-05-31","recentHigh":{"within3M":true,"label":"최근 최고가","price":60500,"date":"2025-10-21","previousHighPrice":50000}},"84㎡":{"avgPrice":64214,"tradeCount":14,"latestPrice":61500,"latestDate":"2026-06-29","recentHigh":{"within3M":true,"label":"최근 최고가","price":67300,"date":"2026-02-02","previousHighPrice":66200}},"59㎡":{"avgPrice":49350,"tradeCount":18,"latestPrice":51800,"latestDate":"2026-07-16","recentHigh":{"within3M":true,"label":"최근 최고가","price":54000,"date":"2026-03-18","previousHighPrice":52500}}}}
