{"kaptCode":"A10023630","aptName":"힐스테이트푸르지오수원","sigunguName":"수원시 팔달구","umdName":"매교동","updatedAt":"2026-06-07","byArea":{"43㎡":{"avgPrice":43733,"tradeCount":12,"latestPrice":42000,"latestDate":"2026-05-23"},"59㎡":{"avgPrice":71716,"tradeCount":29,"latestPrice":64500,"latestDate":"2026-05-19"},"74㎡":{"avgPrice":79250,"tradeCount":5,"latestPrice":83000,"latestDate":"2026-05-30"},"49㎡":{"avgPrice":59600,"tradeCount":5,"latestPrice":63000,"latestDate":"2026-05-13"},"84㎡":{"avgPrice":86221,"tradeCount":7,"latestPrice":84500,"latestDate":"2026-05-22"},"39㎡":{"avgPrice":42750,"tradeCount":2,"latestPrice":44000,"latestDate":"2026-05-29"}}}
