{"kaptCode":"A10024736","aptName":"웰링턴","sigunguName":"의정부시","umdName":"용현동","updatedAt":"2026-06-18","byArea":{"45㎡":{"avgPrice":17050,"tradeCount":4,"latestPrice":17000,"latestDate":"2026-05-16","recentHigh":{"within3M":true,"label":"최근 최고가","price":17300,"date":"2025-12-18","previousHighPrice":16900}},"60㎡":{"avgPrice":20500,"tradeCount":2,"latestPrice":21000,"latestDate":"2025-11-20","recentHigh":{"within3M":true,"label":"최근 최고가","price":21000,"date":"2025-11-20","previousHighPrice":20000}},"59㎡":{"avgPrice":19265,"tradeCount":2,"latestPrice":18850,"latestDate":"2026-04-16"}}}
