{"kaptCode":"A10023630","aptName":"힐스테이트푸르지오수원","sigunguName":"수원시 팔달구","umdName":"매교동","updatedAt":"2026-06-02","byArea":{"43㎡":{"avgPrice":43891,"tradeCount":11,"latestPrice":45400,"latestDate":"2026-05-21"},"59㎡":{"avgPrice":71688,"tradeCount":28,"latestPrice":64500,"latestDate":"2026-05-19"},"74㎡":{"avgPrice":78313,"tradeCount":4,"latestPrice":81000,"latestDate":"2026-04-23"},"49㎡":{"avgPrice":59600,"tradeCount":5,"latestPrice":63000,"latestDate":"2026-05-13"},"84㎡":{"avgPrice":86508,"tradeCount":6,"latestPrice":91000,"latestDate":"2026-05-11"},"39㎡":{"avgPrice":42750,"tradeCount":2,"latestPrice":44000,"latestDate":"2026-05-29"}}}
