{"kaptCode":"A14003105","aptName":"한강(대우)","sigunguName":"용산구","umdName":"이촌동","updatedAt":"2026-07-09","byArea":{"84㎡":{"avgPrice":272250,"tradeCount":12,"latestPrice":258000,"latestDate":"2026-05-21","recentHigh":{"within3M":true,"label":"최근 최고가","price":287500,"date":"2025-11-06","previousHighPrice":286500}},"60㎡":{"avgPrice":240500,"tradeCount":3,"latestPrice":240000,"latestDate":"2026-04-13","recentHigh":{"within3M":true,"label":"최근 최고가","price":242000,"date":"2026-01-09","previousHighPrice":239500}},"134㎡":{"avgPrice":315000,"tradeCount":2,"latestPrice":300000,"latestDate":"2026-05-07"},"135㎡":{"avgPrice":331467,"tradeCount":3,"latestPrice":327000,"latestDate":"2026-06-13"}}}
