{"kaptCode":"A40579706","aptName":"에코메트로5","sigunguName":"남동구","umdName":"논현동","updatedAt":"2026-07-05","byArea":{"143㎡":{"avgPrice":67900,"tradeCount":3,"latestPrice":71000,"latestDate":"2026-05-16","recentHigh":{"within3M":true,"label":"최근 최고가","price":71000,"date":"2026-05-16","previousHighPrice":66700}},"84㎡":{"avgPrice":55833,"tradeCount":30,"latestPrice":59200,"latestDate":"2026-06-19","recentHigh":{"within3M":true,"label":"최근 최고가","price":61400,"date":"2026-02-03","previousHighPrice":59800}},"101㎡":{"avgPrice":60331,"tradeCount":8,"latestPrice":60000,"latestDate":"2026-06-25","recentHigh":{"within3M":true,"label":"최근 최고가","price":62500,"date":"2025-11-01","previousHighPrice":61900}}}}
