{"kaptCode":"A41131211","aptName":"산들마을3단지","sigunguName":"고양시 일산서구","umdName":"일산동","updatedAt":"2026-07-05","byArea":{"116㎡":{"avgPrice":49350,"tradeCount":6,"latestPrice":46000,"latestDate":"2026-04-09","recentHigh":{"within3M":true,"label":"최근 최고가","price":54800,"date":"2026-03-18","previousHighPrice":51000}},"84㎡":{"avgPrice":41238,"tradeCount":8,"latestPrice":43000,"latestDate":"2026-06-01","recentHigh":{"within3M":true,"label":"최근 최고가","price":43500,"date":"2025-09-12","previousHighPrice":40000}},"134㎡":{"avgPrice":50500,"tradeCount":8,"latestPrice":50000,"latestDate":"2026-06-09","recentHigh":{"within3M":true,"label":"최근 최고가","price":62000,"date":"2026-02-12","previousHighPrice":57000}}}}
