{"kaptCode":"A43107002","aptName":"영풍","sigunguName":"안양시 동안구","umdName":"평촌동","updatedAt":"2026-06-23","byArea":{"36㎡":{"avgPrice":29460,"tradeCount":5,"latestPrice":28000,"latestDate":"2026-04-21","recentHigh":{"within3M":true,"label":"최근 최고가","price":30500,"date":"2026-04-04","previousHighPrice":29900}},"84㎡":{"avgPrice":60860,"tradeCount":10,"latestPrice":62000,"latestDate":"2026-06-13","recentHigh":{"within3M":true,"label":"최근 최고가","price":67000,"date":"2026-04-25","previousHighPrice":65000}}}}
