{"kaptCode":"A44384808","aptName":"매탄위브하늘채","sigunguName":"수원시 영통구","umdName":"매탄동","updatedAt":"2026-06-30","byArea":{"59㎡":{"avgPrice":61330,"tradeCount":63,"latestPrice":65000,"latestDate":"2026-05-23","recentHigh":{"within3M":true,"label":"최근 최고가","price":68900,"date":"2026-04-08","previousHighPrice":68000}},"84㎡":{"avgPrice":74347,"tradeCount":103,"latestPrice":73000,"latestDate":"2026-06-20","recentHigh":{"within3M":true,"label":"최근 최고가","price":81800,"date":"2026-06-17","previousHighPrice":81000}},"103㎡":{"avgPrice":83542,"tradeCount":31,"latestPrice":87000,"latestDate":"2026-05-30","recentHigh":{"within3M":true,"label":"최근 최고가","price":90000,"date":"2026-05-22","previousHighPrice":88500}},"72㎡":{"avgPrice":69417,"tradeCount":6,"latestPrice":71000,"latestDate":"2026-05-16"},"128㎡":{"avgPrice":90717,"tradeCount":6,"latestPrice":93500,"latestDate":"2026-06-03","recentHigh":{"within3M":true,"label":"최근 최고가","price":93500,"date":"2026-06-03","previousHighPrice":92500}}}}
