{"kaptCode":"A44576905","aptName":"진안골마을주공10단지","sigunguName":"화성시 병점구","umdName":"진안동","updatedAt":"2026-07-09","byArea":{"59㎡":{"avgPrice":30418,"tradeCount":36,"latestPrice":29500,"latestDate":"2026-07-07","recentHigh":{"within3M":true,"label":"최근 최고가","price":34600,"date":"2025-11-19","previousHighPrice":32750}},"51㎡":{"avgPrice":28175,"tradeCount":22,"latestPrice":27400,"latestDate":"2026-06-29","recentHigh":{"within3M":true,"label":"최근 최고가","price":30000,"date":"2026-02-27","previousHighPrice":29500}}}}
