{"kaptCode":"A44517003","aptName":"롯데캐슬","sigunguName":"화성시 동탄구","umdName":"석우동","updatedAt":"2026-05-19","byArea":{"87㎡":{"avgPrice":74167,"tradeCount":18,"latestPrice":80000,"latestDate":"2026-05-06"},"111㎡":{"avgPrice":83960,"tradeCount":5,"latestPrice":90000,"latestDate":"2026-03-14"},"99㎡":{"avgPrice":73457,"tradeCount":14,"latestPrice":53500,"latestDate":"2026-03-18"},"96㎡":{"avgPrice":82067,"tradeCount":12,"latestPrice":84500,"latestDate":"2026-04-28"},"105㎡":{"avgPrice":80233,"tradeCount":3,"latestPrice":83000,"latestDate":"2026-02-07"},"129㎡":{"avgPrice":92550,"tradeCount":4,"latestPrice":89000,"latestDate":"2026-05-06"},"109㎡":{"avgPrice":83386,"tradeCount":7,"latestPrice":84900,"latestDate":"2026-05-08"}}}
