{"kaptCode":"A44697610","aptName":"죽현마을동원로얄듀크","sigunguName":"용인시 기흥구","umdName":"보정동","updatedAt":"2026-07-05","byArea":{"84㎡":{"avgPrice":113321,"tradeCount":34,"latestPrice":122000,"latestDate":"2026-06-23","recentHigh":{"within3M":true,"label":"최근 최고가","price":135000,"date":"2026-05-18","previousHighPrice":129000}},"152㎡":{"avgPrice":138760,"tradeCount":5,"latestPrice":148500,"latestDate":"2026-05-18","recentHigh":{"within3M":true,"label":"최근 최고가","price":148500,"date":"2026-05-18","previousHighPrice":144000}},"125㎡":{"avgPrice":141167,"tradeCount":6,"latestPrice":147000,"latestDate":"2026-06-12","recentHigh":{"within3M":true,"label":"최근 최고가","price":150000,"date":"2026-06-09","previousHighPrice":145000}}}}
