{"kaptCode":"A44656209","aptName":"교동마을현대필그린","sigunguName":"용인시 기흥구","umdName":"마북동","updatedAt":"2026-07-12","byArea":{"84㎡":{"avgPrice":47750,"tradeCount":12,"latestPrice":49000,"latestDate":"2026-06-18","recentHigh":{"within3M":true,"label":"최근 최고가","price":51800,"date":"2026-05-18","previousHighPrice":49000}},"134㎡":{"avgPrice":57273,"tradeCount":11,"latestPrice":57000,"latestDate":"2026-06-30","recentHigh":{"within3M":true,"label":"최근 최고가","price":64000,"date":"2026-02-06","previousHighPrice":59000}},"186㎡":{"avgPrice":69000,"tradeCount":3,"latestPrice":70000,"latestDate":"2026-03-23","recentHigh":{"within3M":true,"label":"최근 최고가","price":70000,"date":"2026-03-23","previousHighPrice":69000}}}}
