{"kaptCode":"A44853609","aptName":"신봉동일하이빌4단지","sigunguName":"용인시 수지구","umdName":"신봉동","updatedAt":"2026-06-17","byArea":{"132㎡":{"avgPrice":90921,"tradeCount":13,"latestPrice":88000,"latestDate":"2026-05-30","recentHigh":{"within3M":true,"label":"최근 최고가","price":93800,"date":"2026-05-28","previousHighPrice":93500}},"84㎡":{"avgPrice":79167,"tradeCount":9,"latestPrice":85000,"latestDate":"2026-03-18","recentHigh":{"within3M":true,"label":"최근 최고가","price":85000,"date":"2026-03-18","previousHighPrice":84000}},"165㎡":{"avgPrice":93000,"tradeCount":3,"latestPrice":94500,"latestDate":"2026-02-02","recentHigh":{"within3M":true,"label":"최근 최고가","price":94500,"date":"2026-02-02","previousHighPrice":92500}}}}
