{"kaptCode":"A44851005","aptName":"래미안이스트팰리스2단지","sigunguName":"용인시 수지구","umdName":"동천동","updatedAt":"2026-07-23","byArea":{"84㎡":{"avgPrice":114622,"tradeCount":9,"latestPrice":118000,"latestDate":"2026-07-04","recentHigh":{"within3M":true,"label":"최근 최고가","price":120000,"date":"2026-05-30","previousHighPrice":119400}},"148㎡":{"avgPrice":120538,"tradeCount":8,"latestPrice":124300,"latestDate":"2026-07-11","recentHigh":{"within3M":true,"label":"최근 최고가","price":125000,"date":"2026-04-15","previousHighPrice":121500}},"119㎡":{"avgPrice":110750,"tradeCount":2,"latestPrice":110000,"latestDate":"2025-11-26"},"172㎡":{"avgPrice":129438,"tradeCount":8,"latestPrice":125000,"latestDate":"2026-05-19","recentHigh":{"within3M":true,"label":"최근 최고가","price":140000,"date":"2026-01-07","previousHighPrice":130000}}}}
