{"kaptCode":"A46374012","aptName":"까치마을(2단지)(주공)","sigunguName":"성남시 분당구","umdName":"구미동","updatedAt":"2026-07-19","byArea":{"58㎡":{"avgPrice":127063,"tradeCount":16,"latestPrice":155000,"latestDate":"2026-06-26","recentHigh":{"within3M":true,"label":"최근 최고가","price":155000,"date":"2026-06-26","previousHighPrice":149500}},"59㎡":{"avgPrice":129850,"tradeCount":10,"latestPrice":154000,"latestDate":"2026-06-17","recentHigh":{"within3M":true,"label":"최근 최고가","price":154000,"date":"2026-06-17","previousHighPrice":148000}},"49㎡":{"avgPrice":106711,"tradeCount":9,"latestPrice":129500,"latestDate":"2026-06-10","recentHigh":{"within3M":true,"label":"최근 최고가","price":129500,"date":"2026-06-10","previousHighPrice":125000}}}}
