{"kaptCode":"A60931207","aptName":"구서동롯데캐슬골드2단지(1049)","sigunguName":"금정구","umdName":"구서동","updatedAt":"2026-06-07","byArea":{"77㎡":{"avgPrice":38900,"tradeCount":2,"latestPrice":32500,"latestDate":"2026-04-21"},"59㎡":{"avgPrice":37233,"tradeCount":3,"latestPrice":39200,"latestDate":"2026-05-10"},"133㎡":{"avgPrice":55500,"tradeCount":2,"latestPrice":51000,"latestDate":"2026-05-11"},"84㎡":{"avgPrice":49825,"tradeCount":4,"latestPrice":54500,"latestDate":"2026-05-23"},"110㎡":{"avgPrice":55200,"tradeCount":2,"latestPrice":53400,"latestDate":"2026-05-12"}}}
