{"kaptCode":"A64178302","aptName":"은아","sigunguName":"창원시 성산구","umdName":"신월동","updatedAt":"2026-05-29","byArea":{"111㎡":{"avgPrice":96000,"tradeCount":2,"latestPrice":96000,"latestDate":"2026-03-25"},"84㎡":{"avgPrice":77571,"tradeCount":7,"latestPrice":77000,"latestDate":"2026-05-23"},"60㎡":{"avgPrice":54400,"tradeCount":3,"latestPrice":54000,"latestDate":"2026-05-12"},"74㎡":{"avgPrice":63225,"tradeCount":2,"latestPrice":62950,"latestDate":"2026-04-06"},"79㎡":{"avgPrice":69250,"tradeCount":2,"latestPrice":70000,"latestDate":"2026-05-23"}}}
