{"kaptCode":"A66092106","aptName":"두산위브","sigunguName":"진주시","umdName":"금산면 장사리","updatedAt":"2026-06-17","byArea":{"84㎡":{"avgPrice":24000,"tradeCount":19,"latestPrice":30000,"latestDate":"2026-05-01","recentHigh":{"within3M":true,"label":"최근 최고가","price":30000,"date":"2026-05-01","previousHighPrice":27000}},"170㎡":{"avgPrice":36800,"tradeCount":2,"latestPrice":36800,"latestDate":"2026-01-20"},"112㎡":{"avgPrice":26843,"tradeCount":7,"latestPrice":28700,"latestDate":"2026-04-14","recentHigh":{"within3M":true,"label":"최근 최고가","price":28700,"date":"2026-04-14","previousHighPrice":28400}},"138㎡":{"avgPrice":29300,"tradeCount":2,"latestPrice":29300,"latestDate":"2026-04-11"}}}
