{"kaptCode":"A70616004","aptName":"사월보성","sigunguName":"수성구","umdName":"사월동","updatedAt":"2026-07-07","byArea":{"59㎡":{"avgPrice":14313,"tradeCount":34,"latestPrice":14000,"latestDate":"2026-07-02","recentHigh":{"within3M":true,"label":"최근 최고가","price":18500,"date":"2026-01-14","previousHighPrice":17500}},"84㎡":{"avgPrice":25577,"tradeCount":13,"latestPrice":26500,"latestDate":"2026-06-12","recentHigh":{"within3M":true,"label":"최근 최고가","price":33000,"date":"2025-09-05","previousHighPrice":27000}}}}
